mir/dlsite/__init__.py
mir/dlsite/api.py
mir/dlsite/workinfo.py
mir.dlsite-0.8.0.dist-info/LICENSE
mir.dlsite-0.8.0.dist-info/METADATA
mir.dlsite-0.8.0.dist-info/WHEEL
mir.dlsite-0.8.0.dist-info/top_level.txt
mir.dlsite-0.8.0.dist-info/RECORD
