Metadata-Version: 2.1
Name: mir.dlsite
Version: 0.8.0
Summary: API for DLsite
Home-page: https://github.com/darkfeline/mir.dlsite
Author: Allen Li
Author-email: darkfeline@felesatra.moe
License: UNKNOWN
Platform: UNKNOWN
Classifier: Development Status :: 4 - Beta
Classifier: Environment :: Console
Classifier: Intended Audience :: Developers
Classifier: Programming Language :: Python :: 3.9
License-File: LICENSE
Requires-Dist: beautifulsoup4 (~=4.6)
Requires-Dist: lxml (~=4.0)
